odoo/addons/l10n_ch_qr_no_amount/README.rst
odoo/addons/l10n_ch_qr_no_amount/__init__.py
odoo/addons/l10n_ch_qr_no_amount/__manifest__.py
odoo/addons/l10n_ch_qr_no_amount/i18n/l10n_ch_qr_no_amount.pot
odoo/addons/l10n_ch_qr_no_amount/models/__init__.py
odoo/addons/l10n_ch_qr_no_amount/models/res_partner_bank.py
odoo/addons/l10n_ch_qr_no_amount/readme/CONTRIBUTORS.rst
odoo/addons/l10n_ch_qr_no_amount/readme/DESCRIPTION.rst
odoo/addons/l10n_ch_qr_no_amount/readme/uSAGE.rst
odoo/addons/l10n_ch_qr_no_amount/report/swissqr_no_amount_report.xml
odoo/addons/l10n_ch_qr_no_amount/static/description/icon.png
odoo/addons/l10n_ch_qr_no_amount/static/description/index.html
odoo/addons/l10n_ch_qr_no_amount/static/src/img/Betragsfeld_Eckmarke.png
odoo/addons/l10n_ch_qr_no_amount/static/src/img/Feld_Betrag_40x15mm.png
odoo/addons/l10n_ch_qr_no_amount/static/src/scss/report_swissqr_no_amount.scss
odoo13_addon_l10n_ch_qr_no_amount-13.0.1.0.1.dev5.dist-info/METADATA
odoo13_addon_l10n_ch_qr_no_amount-13.0.1.0.1.dev5.dist-info/WHEEL
odoo13_addon_l10n_ch_qr_no_amount-13.0.1.0.1.dev5.dist-info/top_level.txt
odoo13_addon_l10n_ch_qr_no_amount-13.0.1.0.1.dev5.dist-info/RECORD
